qusim/__init__.py
qusim/DataPlot/__init__.py
qusim/DataPlot/plot_lib.py
qusim/DataPlot/plot_tomo.py
qusim/DataView/__init__.py
qusim/DataView/qtplot.py
qusim/DataView/socket_server.py
qusim/DataView/test_scan.py
qusim/DataView/tracer.py
qusim/DataView/tracer_device.py
qusim/DataView/viewer.py
qusim/Instruments/__init__.py
qusim/Instruments/angle.py
qusim/Instruments/avoid_crossing.py
qusim/Instruments/stochastic_gen.py
qusim/Instruments/tools.py
qusim/Instruments/tunablec.py
qusim/PulseGen/__init__.py
qusim/PulseGen/edges.py
qusim/PulseGen/noise_gen.py
qusim/PulseGen/pulse_buffer.py
qusim/PulseGen/pulse_shape.py
qusim/PulseGen/pulse_waveform.py
qusim/Scans/__init__.py
qusim/Scans/qsrun.py
qusim/Scans/scan1D.py
qusim/Scans/scan2D.py
qusim/Scans/scanND.py
qusim/System/__init__.py
qusim/System/arb_qubit_system.py
qusim/System/transmon_system.py
qusim/Utils/__init__.py
qusim/Utils/instr.py
qusim/Utils/qsave.py
qusim-1.0.3.dist-info/LICENSE
qusim-1.0.3.dist-info/METADATA
qusim-1.0.3.dist-info/WHEEL
qusim-1.0.3.dist-info/top_level.txt
qusim-1.0.3.dist-info/RECORD
