Metadata-Version: 2.1
Name: qusim
Version: 1.0.3
Summary: A simple example package
Home-page: https://github.com/RunawayFancy/QuSim
Author: Jiheng Duan
Author-email: jiheng.duan@rochester.edu
License: MIT
Classifier: License :: OSI Approved :: MIT License
Classifier: Programming Language :: Python :: 3.10
License-File: LICENSE
Requires-Dist: matplotlib ==3.8.3
Requires-Dist: mpmath ==1.3.0
Requires-Dist: numpy ==1.26.4
Requires-Dist: pillow ==10.2.0
Requires-Dist: qutip ==4.7.5
Requires-Dist: scipy ==1.12.0
Requires-Dist: sympy ==1.12
Requires-Dist: tqdm ==4.66.2
Requires-Dist: ipython ==8.22.2
Requires-Dist: ipykernel ==6.29.3
Requires-Dist: ipywidgets ==7.6.5
